NEIST_APG1/__init__.py
NEIST_APG1/__main__.py
NEIST_APG1/model1.py
NEIST_APG1/model2.py
NEIST_APG1-0.1.dist-info/METADATA
NEIST_APG1-0.1.dist-info/WHEEL
NEIST_APG1-0.1.dist-info/top_level.txt
NEIST_APG1-0.1.dist-info/RECORD
